pilosa/__init__.py
pilosa/client.py
pilosa/exceptions.py
pilosa/imports.py
pilosa/orm.py
pilosa/response.py
pilosa/validator.py
pilosa/version.py
pilosa/internal/__init__.py
pilosa/internal/public_pb2.py
pilosa-1.3.1.dist-info/LICENSE
pilosa-1.3.1.dist-info/METADATA
pilosa-1.3.1.dist-info/WHEEL
pilosa-1.3.1.dist-info/top_level.txt
pilosa-1.3.1.dist-info/RECORD
